netspeedlogger/__init__.py
netspeedlogger/app.py
netspeedlogger/cli.py
netspeedlogger/netspeedlogger.py
netspeedlogger-0.1.3.dist-info/entry_points.txt
netspeedlogger-0.1.3.dist-info/LICENSE
netspeedlogger-0.1.3.dist-info/WHEEL
netspeedlogger-0.1.3.dist-info/METADATA
netspeedlogger-0.1.3.dist-info/RECORD
